ose_plugin_bcio/BCIOSearchClient.py
ose_plugin_bcio/BCIOSearchReleaseStep.py
ose_plugin_bcio/BCIOSearchService.py
ose_plugin_bcio/__init__.py
ose_plugin_bcio/scripts/cleanup_bcio_vocab.py
ose_plugin_bcio/scripts/import_missing_externals.py
ose_plugin_bcio/scripts/set_pre_proposed_curation_status.py
ose_plugin_bcio/scripts/update_imports_to_latest_versions.py
ose_plugin_bcio/static/ose-plugin-bcio.js
ose_plugin_bcio/static/ose-plugin-bcio.umd.cjs
ose_plugin_bcio-0.2.5.dist-info/METADATA
ose_plugin_bcio-0.2.5.dist-info/WHEEL
ose_plugin_bcio-0.2.5.dist-info/entry_points.txt
ose_plugin_bcio-0.2.5.dist-info/top_level.txt
ose_plugin_bcio-0.2.5.dist-info/RECORD
