Metadata-Version: 2.4
Name: ose-plugin-bcio
Version: 0.2.5
Summary: Plugin for BCIO services and workflows
Requires-Python: >=3.12
Requires-Dist: ose-core==0.2.5
Requires-Dist: ose-plugin-hbcp==0.2.5
Requires-Dist: GitHub-Flask
Requires-Dist: Flask-SQLAlchemy==3.1.1
